src/dffe.v
/*
 * D Flip-Flop w/ enable that can store a single bit of information.
 *
 * Usage
 * dffe bit0(q[0],d[0],clk,enable,reset);
 * dffe bit1(q[1],d[1],clk,enable,reset);
 *
 */

module dffe (
    output reg  q,       //! Current state of the flip-flop
    input  wire d,       //! Next state to be taken by the flip-flop on the next clock edge
    input  wire clock,   //! Clock signal, positive edge-sensitive
    input  wire enable,  //! Load new value? (yes = 1, no = 0)
    input  wire reset    //! Asynchronous reset
);
  always @(reset) if (reset == 1'b1) q <= 0;
  always @(posedge clock) if ((reset == 1'b0) && (enable == 1'b1)) q <= d;
endmodule

src/control_unit.v
`define add 4'hA
`define sub 4'hB
`define mul 4'hC
`define div 4'hD
`define equal 4'hE
`define clear 4'hF

module control_unit (
    output display,  //! OLED Display
    output reg [31:0] operandF = 0,
    output reg [31:0] operandS = 0,
    input [3:0] button,  //! The button pressed by the user (0-9, +, -, *, /, =)
    input is_pressed_next,  // When the user presses a button    
    input clock,  // positive edge
    input reset  // When we initialize the calculator and reset
);

  // operandF = 0;  //! The first number shown on the display
  // operandS = 0;  //! The second number shown on the display
  reg [1:0] alu_op = 0;  //! state 0 = +, state 1 = -, state 2 = *, state 3 = /

  // output of the DFFE's state
  wire s_initial;  // state 0
  wire s_operandF;  // state 1
  wire s_operation;  // state 2
  wire s_operandS;  // state 3
  wire s_result;  // state 4

  // input of the DFFE's next state
  wire next_initial;
  wire next_operandF;
  wire next_operation;
  wire next_operandS;
  wire next_result;
  wire button_pressed = (is_pressed == 0 & is_pressed_next == 1);

  wire is_number = button_pressed & (button >= 4'h0 && button <= 4'h9);
  wire is_equal = button_pressed & (button == `equal);
  wire is_op = button_pressed & (button == `add | button == `sub | button == `mul | button == `div);
  wire is_clear = button_pressed & (button == `clear);
  wire is_pressed;
  // if state is initial or operandF, 

  always @(posedge clock) begin
    if (s_initial && is_number) begin
      operandF = button;
    end else if (s_operandF && is_number) begin
      operandF = operandF * 10 + button;
    end else if ((s_operandF || s_result) && is_op) begin
      if (button == `add) begin
        alu_op = 0;
      end else if (button == `sub) begin
        alu_op = 1;
      end else if (button == `mul) begin
        alu_op = 2;
      end else if (button == `div) begin
        alu_op = 3;
      end
    end else if (s_operation && is_number) begin
      operandS = button;
    end else if (s_operandS && is_number) begin
      operandS = operandS * 10 + button;
    end else if (s_operandS && is_equal) begin
      if (alu_op == 0) begin
        operandF = operandF + operandS;
      end else if (alu_op == 1) begin
        operandF = operandF - operandS;
      end else if (alu_op == 2) begin
        operandF = operandF * operandS;
      end else if (alu_op == 3) begin
        operandF = operandF / operandS;
      end
      operandS = 0;
      alu_op   = 0;
    end else if (is_clear) begin
      operandF = 0;
      operandS = 0;
      alu_op   = 0;
    end
  end

  assign display = s_operandS;

  dffe is_pressed_state (
      is_pressed,
      is_pressed_next,
      clock,
      1'b1,
      1'b0
  );  // 1 clock interval delay between button presses

  assign next_initial = reset | is_clear | (is_equal && s_initial) | (is_op && s_initial) | (~button_pressed & s_initial);
  assign next_operandF = ((is_number && s_initial) | (is_number && s_operandF) | (is_equal && s_operandF) | (~button_pressed & s_operandF)) && ~reset;
  assign next_operation = ((is_op && s_operandF) | (is_op && s_operation) | (is_equal && s_operation) | (is_op && s_result) | (~button_pressed & s_operation)) && ~reset;
  assign next_operandS =  ((is_number && s_operation)  | (is_number && s_operandS) | (is_op && s_operandS) | (~button_pressed & s_operandS) ) && ~reset;
  assign next_result = ((is_equal && s_operandS) | (is_equal && s_result) | (is_number && s_result) | (~button_pressed & s_result)) && ~reset;


  // One hot encoding
  dffe fsInitial (
      s_initial,
      next_initial,
      clock,
      1'b1,
      1'b0
  );

  dffe fsOperandF (
      s_operandF,
      next_operandF,
      clock,
      1'b1,
      1'b0
  );

  dffe fsOperation (
      s_operation,
      next_operation,
      clock,
      1'b1,
      1'b0
  );

  dffe fsOperandS (
      s_operandS,
      next_operandS,
      clock,
      1'b1,
      1'b0
  );

  dffe fsResult (
      s_result,
      next_result,
      clock,
      1'b1,
      1'b0
  );




endmodule

src/control_unit_tb.v
`timescale 1ns / 1ps

module control_unit_test;

  // Signal Declarations
  reg [3:0] button = 4'h0;
  reg is_pressed_next = 0;
  reg clock = 0;
  reg reset = 1;




  // Instantiate Device Under Test (DUT)
  control_unit dut (
      .button(button),
      .is_pressed_next(is_pressed_next),
      .clock(clock),
      .reset(reset)
  );

  // Clock generation (100 MHz)
  always #5 clock = ~clock;

  // Initial block for simulation control
  initial begin
    // Set up VCD file for waveform dump
    $dumpfile("bin/control_unit.vcd");
    $dumpvars;

    // Reset sequence
    #10 reset = 0;

    #10 button = `clear;
    is_pressed_next = 1;

    #10 is_pressed_next = 0;

    #10 button = 4'h8;
    is_pressed_next = 1;
    #10 is_pressed_next = 0;

    #10 button = 4'h9;
    is_pressed_next = 1;
    #10 is_pressed_next = 0;

    #10 button = `clear;
    is_pressed_next = 1;
    #10 is_pressed_next = 0;

    #10 button = 4'h3;
    is_pressed_next = 1;
    #10 is_pressed_next = 0;



    #10 button = `add;
    is_pressed_next = 1;

    #20 is_pressed_next = 0;

    #10 button = 4'h2;
    is_pressed_next = 1;

    #10 is_pressed_next = 0;

    #10 button = `equal;
    is_pressed_next = 1;

    #10 is_pressed_next = 0;

    #10 button = `clear;
    is_pressed_next = 1;

    #10 is_pressed_next = 0;

    #10 button = 4'h7;
    is_pressed_next = 1;
    #10 is_pressed_next = 0;

    #10 button = `div;
    is_pressed_next = 1;
    #10 is_pressed_next = 0;

    #10 button = 4'h4;
    is_pressed_next = 1;
    #10 is_pressed_next = 0;

    #10 button = `equal;
    is_pressed_next = 1;
    #10 is_pressed_next = 0;

    #10 button = `add;
    is_pressed_next = 1;
    #10 is_pressed_next = 0;

    #10 button = 4'h7;
    is_pressed_next = 1;
    #10 is_pressed_next = 0;

    #10 button = `equal;
    is_pressed_next = 1;
    #10 is_pressed_next = 0;


    #10 button = `clear;
    is_pressed_next = 1;
    #10 is_pressed_next = 0;



    // End simulation after a specified time
    #50 $finish;
  end

endmodule

bin/control_unit.vcd
$date
	Tue Nov 14 19:53:04 2023
$end
$version
	Icarus Verilog
$end
$timescale
	1ps
$end
$scope module control_unit_test $end
$var reg 4 ! button [3:0] $end
$var reg 1 " clock $end
$var reg 1 # is_pressed_next $end
$var reg 1 $ reset $end
$scope module dut $end
$var wire 4 % button [3:0] $end
$var wire 1 & button_pressed $end
$var wire 1 " clock $end
$var wire 1 ' display $end
$var wire 1 ( is_clear $end
$var wire 1 ) is_equal $end
$var wire 1 * is_number $end
$var wire 1 + is_op $end
$var wire 1 # is_pressed_next $end
$var wire 1 , next_initial $end
$var wire 1 - next_operandF $end
$var wire 1 . next_operandS $end
$var wire 1 / next_operation $end
$var wire 1 0 next_result $end
$var wire 1 $ reset $end
$var wire 1 1 s_result $end
$var wire 1 2 s_operation $end
$var wire 1 3 s_operandS $end
$var wire 1 4 s_operandF $end
$var wire 1 5 s_initial $end
$var wire 1 6 is_pressed $end
$var reg 2 7 alu_op [1:0] $end
$var reg 32 8 operandF [31:0] $end
$var reg 32 9 operandS [31:0] $end
$scope module fsInitial $end
$var wire 1 " clock $end
$var wire 1 , d $end
$var wire 1 : enable $end
$var wire 1 ; reset $end
$var reg 1 5 q $end
$upscope $end
$scope module fsOperandF $end
$var wire 1 " clock $end
$var wire 1 - d $end
$var wire 1 < enable $end
$var wire 1 = reset $end
$var reg 1 4 q $end
$upscope $end
$scope module fsOperandS $end
$var wire 1 " clock $end
$var wire 1 . d $end
$var wire 1 > enable $end
$var wire 1 ? reset $end
$var reg 1 3 q $end
$upscope $end
$scope module fsOperation $end
$var wire 1 " clock $end
$var wire 1 / d $end
$var wire 1 @ enable $end
$var wire 1 A reset $end
$var reg 1 2 q $end
$upscope $end
$scope module fsResult $end
$var wire 1 " clock $end
$var wire 1 0 d $end
$var wire 1 B enable $end
$var wire 1 C reset $end
$var reg 1 1 q $end
$upscope $end
$scope module is_pressed_state $end
$var wire 1 " clock $end
$var wire 1 # d $end
$var wire 1 D enable $end
$var wire 1 E reset $end
$var reg 1 6 q $end
$upscope $end
$upscope $end
$upscope $end
$enddefinitions $end
$comment Show the parameter values. $end
$dumpall
$end
#0
$dumpvars
0E
1D
0C
1B
0A
1@
0?
1>
0=
1<
0;
1:
b0 9
b0 8
b0 7
x6
x5
x4
x3
x2
x1
00
0/
0.
0-
1,
0+
0*
0)
0(
x'
0&
b0 %
1$
0#
0"
b0 !
$end
#5000
06
15
04
02
0'
03
01
1"
#10000
0"
0$
#15000
1"
#20000
1,
1(
1&
0"
1#
b1111 !
b1111 %
#25000
0(
0&
16
1"
#30000
0"
0#
#35000
06
1"
#40000
1-
0,
1*
1&
0"
1#
b1000 !
b1000 %
#45000
0*
0&
16
05
14
b1000 8
1"
#50000
0"
0#
#55000
06
1"
#60000
1-
1*
1&
0"
1#
b1001 !
b1001 %
#65000
0*
0&
16
b1011001 8
1"
#70000
0"
0#
#75000
06
1"
#80000
1,
0-
1(
1&
0"
1#
b1111 !
b1111 %
#85000
0(
0&
16
15
04
b0 8
1"
#90000
0"
0#
#95000
06
1"
#100000
1-
0,
1*
1&
0"
1#
b11 !
b11 %
#105000
0*
0&
16
05
14
b11 8
1"
#110000
0"
0#
#115000
06
1"
#120000
1/
0-
1+
1&
0"
1#
b1010 !
b1010 %
#125000
0+
0&
16
04
12
1"
#130000
0"
#135000
1"
#140000
0"
0#
#145000
06
1"
#150000
1.
0/
0+
1*
1&
0"
1#
b10 !
b10 %
#155000
0*
0&
1'
13
02
16
b10 9
1"
#160000
0"
0#
#165000
06
1"
#170000
10
0.
1)
1&
0"
1#
b1110 !
b1110 %
#175000
0)
0&
11
0'
03
16
b0 9
b101 8
1"
#180000
0"
0#
#185000
06
1"
#190000
1,
00
1(
1&
0"
1#
b1111 !
b1111 %
#195000
0(
0&
01
15
16
b0 8
1"
#200000
0"
0#
#205000
06
1"
#210000
1-
0,
1*
1&
0"
1#
b111 !
b111 %
#215000
0*
0&
14
05
16
b111 8
1"
#220000
0"
0#
#225000
06
1"
#230000
1/
0-
1+
1&
0"
1#
b1101 !
b1101 %
#235000
0+
0&
12
04
16
b11 7
1"
#240000
0"
0#
#245000
06
1"
#250000
1.
0/
1*
1&
0"
1#
b100 !
b100 %
#255000
0*
0&
1'
13
02
16
b100 9
1"
#260000
0"
0#
#265000
06
1"
#270000
10
0.
1)
1&
0"
1#
b1110 !
b1110 %
#275000
0)
0&
11
0'
03
16
b0 7
b0 9
b1 8
1"
#280000
0"
0#
#285000
06
1"
#290000
1/
00
1+
1&
0"
1#
b1010 !
b1010 %
#295000
0+
0&
01
12
16
1"
#300000
0"
0#
#305000
06
1"
#310000
1.
0/
0+
1*
1&
0"
1#
b111 !
b111 %
#315000
0*
0&
1'
13
02
16
b111 9
1"
#320000
0"
0#
#325000
06
1"
#330000
10
0.
1)
1&
0"
1#
b1110 !
b1110 %
#335000
0)
0&
11
0'
03
16
b0 9
b1000 8
1"
#340000
0"
0#
#345000
06
1"
#350000
1,
00
1(
1&
0"
1#
b1111 !
b1111 %
#355000
0(
0&
01
15
16
b0 8
1"
#360000
0"
0#
#365000
06
1"
