src/control_unit.v
// Define operation codes
`define ZERO 4'h0
`define ONE 4'h1
`define TWO 4'h2
`define THREE 4'h3
`define MEM_STORE 4'h1
`define MEM_LOAD 4'h2
`define MEM_CLEAR 4'h3
`define FOUR 4'h4
`define FIVE 4'h5
`define SIX 4'h6
`define SEVEN 4'h7
`define EIGHT 4'h8
`define NINE 4'h9
`define ADD_DIV 4'hA
`define SUB_DEC 4'hB
`define MUL_NEG 4'hC
`define TOGGLE 4'hD
`define EQUAL 4'hE
`define CLEAR 4'hF

module control_unit (
    output                   display,          // OLED Display output
    output reg signed [63:0] operandF = 0,     // First operand
    output reg signed [63:0] operandS = 0,     // Second operand
    input             [ 3:0] button,           // User input button (0-9, +, -, *, /, =)
    input                    is_pressed_next,  // Button press signal
    input                    clock,            // Clock signal
    input                    reset             // Reset signal
);

  reg [1:0] alu_op = 0;  // ALU operation state (0: +, 1: -, 2: *, 3: /)

  // State outputs
  reg s_initial, s_operandF, s_operation, s_operandS, s_result;
  reg is_pressed = 0;  // Initialize because it broke under Ryan
  reg toggle = 0;
  reg negative = 0;
  reg [1:0] decimal = 0;
  reg signed [63:0] stored_value = 0;
  reg stored_negative = 0;

  localparam fixed_point_length = 2;



  // Next state inputs
  wire next_initial, next_operandF, next_operation, next_operandS, next_result;


  wire button_pressed = (is_pressed == 0 && is_pressed_next == 1);
  wire is_symbol = button_pressed && ((button == `SUB_DEC && toggle) || (button == `MUL_NEG && toggle));
  wire is_number = button_pressed && ((button >= `ZERO && button <= `NINE) && ~toggle);
  wire is_equal = button_pressed && (button == `EQUAL);
  wire is_op = button_pressed && (button == `ADD_DIV || (button == `SUB_DEC && ~toggle)  ||  ( button == `MUL_NEG && ~toggle));
  wire is_clear = button_pressed && (button == `CLEAR);
  wire is_toggled = button_pressed && (button == `TOGGLE);
  wire is_mem_op = button_pressed && toggle && (button == `MEM_STORE || button == `MEM_LOAD || button == `MEM_CLEAR);

  always @(posedge clock or posedge reset) begin
    if (reset) begin
      s_initial <= 1;
      s_operandF <= 0;
      s_operation <= 0;
      s_operandS <= 0;
      s_result <= 0;
      is_pressed <= 0;
      toggle <= 0;
      negative <= 0;
      decimal <= 0;
      stored_value <= 0;
    end else begin
      s_initial <= next_initial;
      s_operandF <= next_operandF;
      s_operation <= next_operation;
      s_operandS <= next_operandS;
      s_result <= next_result;
      is_pressed <= is_pressed_next;
    end
  end

  assign next_initial = reset || is_clear || (is_equal && s_initial) || 
                                             (is_op && s_initial) || 
                                             (~button_pressed && s_initial) || 
                                             (s_initial && is_toggled);
  assign next_operandF = ((is_number && s_initial) || 
                          (is_number && s_operandF) || 
                          (is_equal && s_operandF) || 
                          (~button_pressed && s_operandF) || 
                          (s_operandF && is_toggled) || 
                          (s_initial && is_symbol) ||
                          (s_operandF && is_symbol) || 
                          (s_initial && is_mem_op) || 
                          (s_operandF && is_mem_op)) && ~reset;
  assign next_operation = ((is_op && s_operandF) || 
                           (is_op && s_operation) || 
                           (is_equal && s_operation) || 
                           (is_op && s_result) || 
                           (~button_pressed && s_operation) || 
                           (s_operation && is_toggled)) && ~reset;
  assign next_operandS =  ((is_number && s_operation) || 
                           (is_number && s_operandS) || 
                           (is_op && s_operandS) || 
                           (~button_pressed && s_operandS) || 
                           (s_operandS && is_toggled) || 
                           (s_operation && is_symbol) ||
                           (s_operandS && is_symbol) || 
                           (s_operation && is_mem_op) ||
                           (s_operandS && is_mem_op)) && ~reset;
  assign next_result = ((is_equal && s_operandS) || 
                        (is_equal && s_result) || 
                        (is_number && s_result) || 
                        (~button_pressed & s_result) || 
                        (s_result && is_toggled) || 
                        (s_result && is_symbol) ||
                        (s_result && is_mem_op)) && ~reset;


  always @(posedge clock) begin
    if (s_initial && is_number) begin
      operandF = button * 10 ** fixed_point_length;
    end else if (is_toggled) begin
      toggle = ~toggle;
    end else if (s_operandF && is_number) begin
      if (decimal) begin
        operandF = operandF + button * 10 ** (fixed_point_length - decimal);
        decimal  = decimal + 1;
      end else begin
        operandF = operandF * 10 + button * 10 ** fixed_point_length;
      end
    end else if ((s_initial || s_operandF) && toggle && is_symbol && (button == `MUL_NEG)) begin
      negative = ~negative;
      toggle   = 0;
    end else if ((s_initial || s_operandF) && toggle && is_symbol && (button == `SUB_DEC)) begin
      if (decimal == 0) begin
        decimal = 1;
      end
      toggle = 0;
    end else if ((s_initial || s_operandF) && toggle && is_mem_op && button == `MEM_LOAD) begin
      operandF = stored_value;
      negative = stored_negative;
      decimal  = fixed_point_length + 1;
      toggle   = 0;
    end else if ((s_operandF || s_result) && is_op) begin
      if (button == `ADD_DIV && toggle == 0) begin
        alu_op = 0;
        if (negative) begin
          operandF = -operandF;
          negative = 0;
        end
        decimal = 0;
      end else if (button == `SUB_DEC && toggle == 0) begin
        alu_op = 1;
        if (negative) begin
          operandF = -operandF;
          negative = 0;
        end
        decimal = 0;
      end else if (button == `MUL_NEG && toggle == 0) begin
        alu_op = 2;
        if (negative) begin
          operandF = -operandF;
          negative = 0;
        end
        decimal = 0;
      end else if (button == `ADD_DIV && toggle == 1) begin
        alu_op = 3;
        if (negative) begin
          operandF = -operandF;
          negative = 0;
        end
        decimal = 0;
      end
      toggle = 0;
    end else if (s_operation && is_number) begin
      operandS = button * 10 ** fixed_point_length;
    end else if (s_operandS && is_number) begin
      if (decimal) begin
        operandS = operandS + button * 10 ** (fixed_point_length - decimal);
        decimal  = decimal + 1;
      end else begin
        operandS = operandS * 10 + button * 10 ** fixed_point_length;
      end
    end else if ((s_operation || s_operandS) && toggle && is_symbol && (button == `MUL_NEG)) begin
      negative = ~negative;
      toggle   = 0;
    end else if ((s_operation || s_operandS) && toggle && is_symbol && (button == `SUB_DEC)) begin
      if (decimal == 0) begin
        decimal = 1;
      end
      toggle = 0;
    end else if ((s_operation || s_operandS) && toggle && is_mem_op && button == `MEM_LOAD) begin
      operandS = stored_value;
      negative = stored_negative;
      decimal  = fixed_point_length + 1;
      toggle   = 0;
    end else if (s_operandS && is_equal) begin
      if (negative) begin
        operandS = -operandS;
        negative = 0;
        decimal  = 0;
      end
      case (alu_op)
        0: operandF = operandF + operandS;
        1: operandF = operandF - operandS;
        2: operandF = (operandF * operandS) / (10 ** fixed_point_length);
        3: operandF = (operandF * (10 ** fixed_point_length) / operandS);
      endcase
      operandS = 0;
      alu_op   = 0;
      toggle   = 0;
      negative = 0;
      decimal  = 0;
    end else if (s_result && toggle && is_mem_op && button == `MEM_STORE) begin
      stored_value = operandF;
      if (operandF < 0) begin
        stored_value = -stored_value;
      end
      stored_negative = (operandF < 0);
      toggle = 0;
    end else if (is_clear) begin
      operandF = 0;
      operandS = 0;
      alu_op   = 0;
      toggle   = 0;
      negative = 0;
      decimal  = 0;
    end else if (toggle && is_mem_op && button == `MEM_CLEAR) begin
      stored_value = 0;
      stored_negative = 0;
      toggle = 0;
    end
  end

  assign display = s_operandS;

endmodule

src/control_unit_tb.v
`timescale 1ns / 1ps

module control_unit_test;

  // Testbench Signals
  reg [3:0] button = 4'h0;
  reg is_pressed_next = 0;
  reg clock = 0;
  reg reset = 1;// we need to remove this so that the control unit always initilizes to the "initial state" when powered

  // Instantiate Device Under Test (DUT)
  control_unit dut (
      .button(button),
      .is_pressed_next(is_pressed_next),
      .clock(clock),
      .reset(reset)
  );

  // Clock generation (100 MHz)
  always #5 clock = ~clock;

  // Function to simulate button press
  task press_button;
    input [3:0] btn;
    begin
      #10 button = btn;
      is_pressed_next = 1;
      #10 is_pressed_next = 0;  // Mimic button press duration
    end
  endtask


  // Initial block for simulation control
  initial begin
    // Setup waveform dump
    $dumpfile("bin/control_unit.vcd");
    $dumpvars;

    // Reset the DUT
    #10 reset = 0;

    // pos + pos
    // 9 + 7 = 16
    press_button(`NINE);
    press_button(`ADD_DIV);
    press_button(`SEVEN);
    press_button(`EQUAL);
    press_button(`CLEAR);

    // pos + neg 
    // 9 + -7 = 2
    press_button(`NINE);
    press_button(`ADD_DIV);
    press_button(`SEVEN);
    press_button(`TOGGLE);
    press_button(`MUL_NEG);
    press_button(`EQUAL);
    press_button(`CLEAR);

    // neg + neg
    // -9 + -7 = -16
    press_button(`NINE);
    press_button(`TOGGLE);
    press_button(`MUL_NEG);
    press_button(`ADD_DIV);
    press_button(`SEVEN);
    press_button(`TOGGLE);
    press_button(`MUL_NEG);
    press_button(`EQUAL);
    press_button(`CLEAR);

    // neg + pos
    // -9 + 7 = -2
    press_button(`NINE);
    press_button(`TOGGLE);
    press_button(`MUL_NEG);
    press_button(`ADD_DIV);
    press_button(`SEVEN);
    press_button(`EQUAL);
    press_button(`CLEAR);

    // pos - pos
    // 9 - 7 = 2
    press_button(`NINE);
    press_button(`SUB_DEC);
    press_button(`SEVEN);
    press_button(`EQUAL);
    press_button(`CLEAR);

    // pos - neg
    // 9 - -7 = 16
    press_button(`NINE);
    press_button(`SUB_DEC);
    press_button(`SEVEN);
    press_button(`TOGGLE);
    press_button(`MUL_NEG);
    press_button(`EQUAL);
    press_button(`CLEAR);


    // neg - neg
    // -9 - -7 = -2
    press_button(`NINE);
    press_button(`TOGGLE);
    press_button(`MUL_NEG);
    press_button(`SUB_DEC);
    press_button(`SEVEN);
    press_button(`TOGGLE);
    press_button(`MUL_NEG);
    press_button(`EQUAL);
    press_button(`CLEAR);

    // neg - pos
    // -9 - 7 = -16
    press_button(`NINE);
    press_button(`TOGGLE);
    press_button(`MUL_NEG);
    press_button(`SUB_DEC);
    press_button(`SEVEN);
    press_button(`EQUAL);
    press_button(`CLEAR);


    // pos * pos
    // 9 * 7 = 63
    press_button(`NINE);
    press_button(`MUL_NEG);
    press_button(`SEVEN);
    press_button(`EQUAL);
    press_button(`CLEAR);


    // pos * neg
    // 9 * -7 = -63
    press_button(`NINE);
    press_button(`MUL_NEG);
    press_button(`SEVEN);
    press_button(`TOGGLE);
    press_button(`MUL_NEG);
    press_button(`EQUAL);
    press_button(`CLEAR);

    // neg * neg
    // -9 * -7 = 63
    press_button(`NINE);
    press_button(`TOGGLE);
    press_button(`MUL_NEG);
    press_button(`MUL_NEG);
    press_button(`SEVEN);
    press_button(`TOGGLE);
    press_button(`MUL_NEG);
    press_button(`EQUAL);
    press_button(`CLEAR);

    // neg * pos
    // -9 * 7 = -63
    press_button(`NINE);
    press_button(`TOGGLE);
    press_button(`MUL_NEG);
    press_button(`MUL_NEG);
    press_button(`SEVEN);
    press_button(`EQUAL);
    press_button(`CLEAR);

    // pos / pos
    // 9 / 7 = 1
    press_button(`NINE);
    press_button(`TOGGLE);
    press_button(`ADD_DIV);
    press_button(`SEVEN);
    press_button(`EQUAL);
    press_button(`CLEAR);

    // pos / neg
    // 9 / -7 = -1
    press_button(`NINE);
    press_button(`TOGGLE);
    press_button(`ADD_DIV);
    press_button(`SEVEN);
    press_button(`TOGGLE);
    press_button(`MUL_NEG);
    press_button(`EQUAL);
    press_button(`CLEAR);

    // neg / neg
    // -9 / -7 = 1
    press_button(`NINE);
    press_button(`TOGGLE);
    press_button(`MUL_NEG);
    press_button(`TOGGLE);
    press_button(`ADD_DIV);
    press_button(`SEVEN);
    press_button(`TOGGLE);
    press_button(`MUL_NEG);
    press_button(`EQUAL);
    press_button(`CLEAR);

    // neg / pos
    // -9 / 7 = -1
    press_button(`NINE);
    press_button(`TOGGLE);
    press_button(`MUL_NEG);
    press_button(`TOGGLE);
    press_button(`ADD_DIV);
    press_button(`SEVEN);
    press_button(`EQUAL);
    press_button(`CLEAR);


    // 2.5 + 3.5
    press_button(`TWO);
    press_button(`TOGGLE);
    press_button(`SUB_DEC);
    press_button(`FIVE);
    press_button(`ADD_DIV);
    press_button(`THREE);
    press_button(`TOGGLE);
    press_button(`SUB_DEC);
    press_button(`FIVE);
    press_button(`EQUAL);
    press_button(`CLEAR);

    // .9 + .7
    press_button(`TOGGLE);
    press_button(`SUB_DEC);
    press_button(`NINE);
    press_button(`ADD_DIV);
    press_button(`TOGGLE);
    press_button(`SUB_DEC);
    press_button(`SEVEN);
    press_button(`EQUAL);
    press_button(`CLEAR);

    // .09 + .07
    press_button(`TOGGLE);
    press_button(`SUB_DEC);
    press_button(`ZERO);
    press_button(`NINE);
    press_button(`ADD_DIV);
    press_button(`TOGGLE);
    press_button(`SUB_DEC);
    press_button(`ZERO);
    press_button(`SEVEN);
    press_button(`EQUAL);
    press_button(`CLEAR);

    // .09 + 4.93 - 5.01
    press_button(`TOGGLE);
    press_button(`SUB_DEC);
    press_button(`ZERO);
    press_button(`NINE);
    press_button(`ADD_DIV);
    press_button(`FOUR);
    press_button(`TOGGLE);
    press_button(`SUB_DEC);
    press_button(`NINE);
    press_button(`THREE);
    press_button(`EQUAL);
    press_button(`SUB_DEC);
    press_button(`FIVE);
    press_button(`TOGGLE);
    press_button(`SUB_DEC);
    press_button(`ZERO);
    press_button(`ONE);
    press_button(`EQUAL);
    press_button(`CLEAR);

    // 5.09 * 1.25
    press_button(`FIVE);
    press_button(`TOGGLE);
    press_button(`SUB_DEC);
    press_button(`ZERO);
    press_button(`NINE);
    press_button(`MUL_NEG);
    press_button(`ONE);
    press_button(`TOGGLE);
    press_button(`SUB_DEC);
    press_button(`TWO);
    press_button(`FIVE);
    press_button(`EQUAL);
    press_button(`CLEAR);

    // -5.09 / 1.25
    press_button(`TOGGLE);
    press_button(`MUL_NEG);
    press_button(`FIVE);
    press_button(`TOGGLE);
    press_button(`SUB_DEC);
    press_button(`ZERO);
    press_button(`NINE);
    press_button(`TOGGLE);
    press_button(`ADD_DIV);
    press_button(`ONE);
    press_button(`TOGGLE);
    press_button(`SUB_DEC);
    press_button(`TWO);
    press_button(`FIVE);
    press_button(`EQUAL);
    press_button(`CLEAR);

    //-.09 / 1.25
    press_button(`TOGGLE);
    press_button(`MUL_NEG);
    press_button(`TOGGLE);
    press_button(`SUB_DEC);
    press_button(`ZERO);
    press_button(`NINE);
    press_button(`TOGGLE);
    press_button(`ADD_DIV);
    press_button(`ONE);
    press_button(`TOGGLE);
    press_button(`SUB_DEC);
    press_button(`TWO);
    press_button(`FIVE);
    press_button(`EQUAL);
    press_button(`CLEAR);

    // 5+3 = 8 -> MEM
    // CLEAR
    // 2 + 5 = 7
    // MEM -> 8 + 4 = 12
    // MEM_CLEAR = 0
    // MEM -> 0 + 4 = 4
    press_button(`FIVE);
    press_button(`ADD_DIV);
    press_button(`THREE);
    press_button(`EQUAL);
    press_button(`TOGGLE);
    press_button(`MEM_STORE);
    press_button(`CLEAR);
    press_button(`TWO);
    press_button(`ADD_DIV);
    press_button(`FIVE);
    press_button(`EQUAL);
    press_button(`CLEAR);
    press_button(`TOGGLE);
    press_button(`MEM_LOAD);
    press_button(`ADD_DIV);
    press_button(`FOUR);
    press_button(`EQUAL);
    press_button(`CLEAR);
    press_button(`TOGGLE);
    press_button(`MEM_CLEAR);
    press_button(`TOGGLE);
    press_button(`MEM_LOAD);
    press_button(`ADD_DIV);
    press_button(`FOUR);
    press_button(`EQUAL);
    press_button(`CLEAR);

    #10 reset = 1;
    // End simulation after a specified time
    #50 $finish;
  end

endmodule

bin/control_unit.vcd
$date
	Sat Dec  2 15:59:57 2023
$end
$version
	Icarus Verilog
$end
$timescale
	1ps
$end
$scope module control_unit_test $end
$var reg 4 ! button [3:0] $end
$var reg 1 " clock $end
$var reg 1 # is_pressed_next $end
$var reg 1 $ reset $end
$scope module dut $end
$var wire 4 % button [3:0] $end
$var wire 1 & button_pressed $end
$var wire 1 " clock $end
$var wire 1 ' display $end
$var wire 1 ( is_clear $end
$var wire 1 ) is_equal $end
$var wire 1 * is_mem_op $end
$var wire 1 + is_number $end
$var wire 1 , is_op $end
$var wire 1 # is_pressed_next $end
$var wire 1 - is_symbol $end
$var wire 1 . is_toggled $end
$var wire 1 / next_initial $end
$var wire 1 0 next_operandF $end
$var wire 1 1 next_operandS $end
$var wire 1 2 next_operation $end
$var wire 1 3 next_result $end
$var wire 1 $ reset $end
$var parameter 32 4 fixed_point_length $end
$var reg 2 5 alu_op [1:0] $end
$var reg 2 6 decimal [1:0] $end
$var reg 1 7 is_pressed $end
$var reg 1 8 negative $end
$var reg 64 9 operandF [63:0] $end
$var reg 64 : operandS [63:0] $end
$var reg 1 ; s_initial $end
$var reg 1 < s_operandF $end
$var reg 1 = s_operandS $end
$var reg 1 > s_operation $end
$var reg 1 ? s_result $end
$var reg 1 @ stored_negative $end
$var reg 64 A stored_value [63:0] $end
$var reg 1 B toggle $end
$upscope $end
$scope task press_button $end
$var reg 4 C btn [3:0] $end
$upscope $end
$upscope $end
$enddefinitions $end
$comment Show the parameter values. $end
$dumpall
b10 4
$end
#0
$dumpvars
bx C
0B
b0 A
0@
0?
0>
0=
0<
1;
b0 :
b0 9
08
07
b0 6
b0 5
03
02
01
00
1/
0.
0-
0,
0+
0*
0)
0(
0'
0&
b0 %
1$
0#
0"
b0 !
$end
#5000
1"
#10000
0"
b1001 C
0$
#15000
1"
#20000
10
0/
1+
1&
0"
1#
b1001 !
b1001 %
#25000
0+
0&
17
1<
0;
b1110000100 9
1"
#30000
0"
b1010 C
0#
#35000
07
1"
#40000
00
12
1,
1&
0"
1#
b1010 !
b1010 %
#45000
0,
0&
17
1>
0<
1"
#50000
0"
b111 C
0#
#55000
07
1"
#60000
11
02
1+
1&
0"
1#
b111 !
b111 %
#65000
0+
0&
17
1'
1=
0>
b1010111100 :
1"
#70000
0"
b1110 C
0#
#75000
07
1"
#80000
13
01
1)
1&
0"
1#
b1110 !
b1110 %
#85000
0)
0&
17
1?
0'
0=
b0 :
b11001000000 9
1"
#90000
0"
b1111 C
0#
#95000
07
1"
#100000
03
1/
1(
1&
0"
1#
b1111 !
b1111 %
#105000
0(
0&
17
0?
1;
b0 9
1"
#110000
0"
b1001 C
0#
#115000
07
1"
#120000
10
0/
1+
1&
0"
1#
b1001 !
b1001 %
#125000
0+
0&
17
1<
0;
b1110000100 9
1"
#130000
0"
b1010 C
0#
#135000
07
1"
#140000
00
12
1,
1&
0"
1#
b1010 !
b1010 %
#145000
0,
0&
17
1>
0<
1"
#150000
0"
b111 C
0#
#155000
07
1"
#160000
11
02
1+
1&
0"
1#
b111 !
b111 %
#165000
0+
0&
17
1'
1=
0>
b1010111100 :
1"
#170000
0"
b1101 C
0#
#175000
07
1"
#180000
1.
1&
0"
1#
b1101 !
b1101 %
#185000
0.
0&
17
1B
1"
#190000
0"
b1100 C
0#
#195000
07
1"
#200000
1-
1&
0"
1#
b1100 !
b1100 %
#205000
0&
17
11
0,
0-
0B
18
1"
#210000
0"
b1110 C
0#
#215000
07
1"
#220000
13
01
1)
1&
0"
1#
b1110 !
b1110 %
#225000
0)
0&
17
1?
0'
0=
b11001000 9
08
b0 :
1"
#230000
0"
b1111 C
0#
#235000
07
1"
#240000
03
1/
1(
1&
0"
1#
b1111 !
b1111 %
#245000
0(
0&
17
0?
1;
b0 9
1"
#250000
0"
b1001 C
0#
#255000
07
1"
#260000
10
0/
1+
1&
0"
1#
b1001 !
b1001 %
#265000
0+
0&
17
1<
0;
b1110000100 9
1"
#270000
0"
b1101 C
0#
#275000
07
1"
#280000
1.
1&
0"
1#
b1101 !
b1101 %
#285000
0.
0&
17
1B
1"
#290000
0"
b1100 C
0#
#295000
07
1"
#300000
1-
1&
0"
1#
b1100 !
b1100 %
#305000
0&
17
02
10
0,
0-
0B
18
1"
#310000
0"
b1010 C
0#
#315000
07
1"
#320000
00
12
1,
1&
0"
1#
b1010 !
b1010 %
#325000
0,
0&
17
1>
0<
08
b1111111111111111111111111111111111111111111111111111110001111100 9
1"
#330000
0"
b111 C
0#
#335000
07
1"
#340000
11
02
1+
1&
0"
1#
b111 !
b111 %
#345000
0+
0&
17
1'
1=
0>
b1010111100 :
1"
#350000
0"
b1101 C
0#
#355000
07
1"
#360000
1.
1&
0"
1#
b1101 !
b1101 %
#365000
0.
0&
17
1B
1"
#370000
0"
b1100 C
0#
#375000
07
1"
#380000
1-
1&
0"
1#
b1100 !
b1100 %
#385000
0&
17
11
0,
0-
0B
18
1"
#390000
0"
b1110 C
0#
#395000
07
1"
#400000
13
01
1)
1&
0"
1#
b1110 !
b1110 %
#405000
0)
0&
17
1?
0'
0=
b1111111111111111111111111111111111111111111111111111100111000000 9
08
b0 :
1"
#410000
0"
b1111 C
0#
#415000
07
1"
#420000
03
1/
1(
1&
0"
1#
b1111 !
b1111 %
#425000
0(
0&
17
0?
1;
b0 9
1"
#430000
0"
b1001 C
0#
#435000
07
1"
#440000
10
0/
1+
1&
0"
1#
b1001 !
b1001 %
#445000
0+
0&
17
1<
0;
b1110000100 9
1"
#450000
0"
b1101 C
0#
#455000
07
1"
#460000
1.
1&
0"
1#
b1101 !
b1101 %
#465000
0.
0&
17
1B
1"
#470000
0"
b1100 C
0#
#475000
07
1"
#480000
1-
1&
0"
1#
b1100 !
b1100 %
#485000
0&
17
02
10
0,
0-
0B
18
1"
#490000
0"
b1010 C
0#
#495000
07
1"
#500000
00
12
1,
1&
0"
1#
b1010 !
b1010 %
#505000
0,
0&
17
1>
0<
08
b1111111111111111111111111111111111111111111111111111110001111100 9
1"
#510000
0"
b111 C
0#
#515000
07
1"
#520000
11
02
1+
1&
0"
1#
b111 !
b111 %
#525000
0+
0&
17
1'
1=
0>
b1010111100 :
1"
#530000
0"
b1110 C
0#
#535000
07
1"
#540000
13
01
1)
1&
0"
1#
b1110 !
b1110 %
#545000
0)
0&
17
1?
0'
0=
b0 :
b1111111111111111111111111111111111111111111111111111111100111000 9
1"
#550000
0"
b1111 C
0#
#555000
07
1"
#560000
03
1/
1(
1&
0"
1#
b1111 !
b1111 %
#565000
0(
0&
17
0?
1;
b0 9
1"
#570000
0"
b1001 C
0#
#575000
07
1"
#580000
10
0/
1+
1&
0"
1#
b1001 !
b1001 %
#585000
0+
0&
17
1<
0;
b1110000100 9
1"
#590000
0"
b1011 C
0#
#595000
07
1"
#600000
12
00
1,
1&
0"
1#
b1011 !
b1011 %
#605000
0,
0&
17
1>
0<
b1 5
1"
#610000
0"
b111 C
0#
#615000
07
1"
#620000
11
02
1+
0,
1&
0"
1#
b111 !
b111 %
#625000
0+
0&
17
1'
1=
0>
b1010111100 :
1"
#630000
0"
b1110 C
0#
#635000
07
1"
#640000
13
01
1)
1&
0"
1#
b1110 !
b1110 %
#645000
0)
0&
17
1?
0'
0=
b0 5
b0 :
b11001000 9
1"
#650000
0"
b1111 C
0#
#655000
07
1"
#660000
03
1/
1(
1&
0"
1#
b1111 !
b1111 %
#665000
0(
0&
17
0?
1;
b0 9
1"
#670000
0"
b1001 C
0#
#675000
07
1"
#680000
10
0/
1+
1&
0"
1#
b1001 !
b1001 %
#685000
0+
0&
17
1<
0;
b1110000100 9
1"
#690000
0"
b1011 C
0#
#695000
07
1"
#700000
12
00
1,
1&
0"
1#
b1011 !
b1011 %
#705000
0,
0&
17
1>
0<
b1 5
1"
#710000
0"
b111 C
0#
#715000
07
1"
#720000
11
02
1+
0,
1&
0"
1#
b111 !
b111 %
#725000
0+
0&
17
1'
1=
0>
b1010111100 :
1"
#730000
0"
b1101 C
0#
#735000
07
1"
#740000
1.
1&
0"
1#
b1101 !
b1101 %
#745000
0.
0&
17
1B
1"
#750000
0"
b1100 C
0#
#755000
07
1"
#760000
1-
1&
0"
1#
b1100 !
b1100 %
#765000
0&
17
11
0,
0-
0B
18
1"
#770000
0"
b1110 C
0#
#775000
07
1"
#780000
13
01
1)
1&
0"
1#
b1110 !
b1110 %
#785000
0)
0&
17
1?
0'
0=
b0 5
b11001000000 9
08
b0 :
1"
#790000
0"
b1111 C
0#
#795000
07
1"
#800000
03
1/
1(
1&
0"
1#
b1111 !
b1111 %
#805000
0(
0&
17
0?
1;
b0 9
1"
#810000
0"
b1001 C
0#
#815000
07
1"
#820000
10
0/
1+
1&
0"
1#
b1001 !
b1001 %
#825000
0+
0&
17
1<
0;
b1110000100 9
1"
#830000
0"
b1101 C
0#
#835000
07
1"
#840000
1.
1&
0"
1#
b1101 !
b1101 %
#845000
0.
0&
17
1B
1"
#850000
0"
b1100 C
0#
#855000
07
1"
#860000
1-
1&
0"
1#
b1100 !
b1100 %
#865000
0&
17
02
10
0,
0-
0B
18
1"
#870000
0"
b1011 C
0#
#875000
07
1"
#880000
12
00
1,
1&
0"
1#
b1011 !
b1011 %
#885000
0,
0&
17
1>
0<
08
b1111111111111111111111111111111111111111111111111111110001111100 9
b1 5
1"
#890000
0"
b111 C
0#
#895000
07
1"
#900000
11
02
1+
0,
1&
0"
1#
b111 !
b111 %
#905000
0+
0&
17
1'
1=
0>
b1010111100 :
1"
#910000
0"
b1101 C
0#
#915000
07
1"
#920000
1.
1&
0"
1#
b1101 !
b1101 %
#925000
0.
0&
17
1B
1"
#930000
0"
b1100 C
0#
#935000
07
1"
#940000
1-
1&
0"
1#
b1100 !
b1100 %
#945000
0&
17
11
0,
0-
0B
18
1"
#950000
0"
b1110 C
0#
#955000
07
1"
#960000
13
01
1)
1&
0"
1#
b1110 !
b1110 %
#965000
0)
0&
17
1?
0'
0=
b0 5
b1111111111111111111111111111111111111111111111111111111100111000 9
08
b0 :
1"
#970000
0"
b1111 C
0#
#975000
07
1"
#980000
03
1/
1(
1&
0"
1#
b1111 !
b1111 %
#985000
0(
0&
17
0?
1;
b0 9
1"
#990000
0"
b1001 C
0#
#995000
07
1"
#1000000
10
0/
1+
1&
0"
1#
b1001 !
b1001 %
#1005000
0+
0&
17
1<
0;
b1110000100 9
1"
#1010000
0"
b1101 C
0#
#1015000
07
1"
#1020000
1.
1&
0"
1#
b1101 !
b1101 %
#1025000
0.
0&
17
1B
1"
#1030000
0"
b1100 C
0#
#1035000
07
1"
#1040000
1-
1&
0"
1#
b1100 !
b1100 %
#1045000
0&
17
02
10
0,
0-
0B
18
1"
#1050000
0"
b1011 C
0#
#1055000
07
1"
#1060000
12
00
1,
1&
0"
1#
b1011 !
b1011 %
#1065000
0,
0&
17
1>
0<
08
b1111111111111111111111111111111111111111111111111111110001111100 9
b1 5
1"
#1070000
0"
b111 C
0#
#1075000
07
1"
#1080000
11
02
1+
0,
1&
0"
1#
b111 !
b111 %
#1085000
0+
0&
17
1'
1=
0>
b1010111100 :
1"
#1090000
0"
b1110 C
0#
#1095000
07
1"
#1100000
13
01
1)
1&
0"
1#
b1110 !
b1110 %
#1105000
0)
0&
17
1?
0'
0=
b0 5
b0 :
b1111111111111111111111111111111111111111111111111111100111000000 9
1"
#1110000
0"
b1111 C
0#
#1115000
07
1"
#1120000
03
1/
1(
1&
0"
1#
b1111 !
b1111 %
#1125000
0(
0&
17
0?
1;
b0 9
1"
#1130000
0"
b1001 C
0#
#1135000
07
1"
#1140000
10
0/
1+
1&
0"
1#
b1001 !
b1001 %
#1145000
0+
0&
17
1<
0;
b1110000100 9
1"
#1150000
0"
b1100 C
0#
#1155000
07
1"
#1160000
00
12
1,
1&
0"
1#
b1100 !
b1100 %
#1165000
0,
0&
17
1>
0<
b10 5
1"
#1170000
0"
b111 C
0#
#1175000
07
1"
#1180000
11
02
1+
1&
0"
1#
b111 !
b111 %
#1185000
0+
0&
17
1'
1=
0>
b1010111100 :
1"
#1190000
0"
b1110 C
0#
#1195000
07
1"
#1200000
13
01
1)
1&
0"
1#
b1110 !
b1110 %
#1205000
0)
0&
17
1?
0'
0=
b0 5
b0 :
b1100010011100 9
1"
#1210000
0"
b1111 C
0#
#1215000
07
1"
#1220000
03
1/
1(
1&
0"
1#
b1111 !
b1111 %
#1225000
0(
0&
17
0?
1;
b0 9
1"
#1230000
0"
b1001 C
0#
#1235000
07
1"
#1240000
10
0/
1+
1&
0"
1#
b1001 !
b1001 %
#1245000
0+
0&
17
1<
0;
b1110000100 9
1"
#1250000
0"
b1100 C
0#
#1255000
07
1"
#1260000
00
12
1,
1&
0"
1#
b1100 !
b1100 %
#1265000
0,
0&
17
1>
0<
b10 5
1"
#1270000
0"
b111 C
0#
#1275000
07
1"
#1280000
11
02
1+
1&
0"
1#
b111 !
b111 %
#1285000
0+
0&
17
1'
1=
0>
b1010111100 :
1"
#1290000
0"
b1101 C
0#
#1295000
07
1"
#1300000
1.
1&
0"
1#
b1101 !
b1101 %
#1305000
0.
0&
17
1B
1"
#1310000
0"
b1100 C
0#
#1315000
07
1"
#1320000
1-
1&
0"
1#
b1100 !
b1100 %
#1325000
0&
17
11
0,
0-
0B
18
1"
#1330000
0"
b1110 C
0#
#1335000
07
1"
#1340000
13
01
1)
1&
0"
1#
b1110 !
b1110 %
#1345000
0)
0&
17
1?
0'
0=
b0 5
b1111111111111111111111111111111111111111111111111110011101100100 9
08
b0 :
1"
#1350000
0"
b1111 C
0#
#1355000
07
1"
#1360000
03
1/
1(
1&
0"
1#
b1111 !
b1111 %
#1365000
0(
0&
17
0?
1;
b0 9
1"
#1370000
0"
b1001 C
0#
#1375000
07
1"
#1380000
10
0/
1+
1&
0"
1#
b1001 !
b1001 %
#1385000
0+
0&
17
1<
0;
b1110000100 9
1"
#1390000
0"
b1101 C
0#
#1395000
07
1"
#1400000
1.
1&
0"
1#
b1101 !
b1101 %
#1405000
0.
0&
17
1B
1"
#1410000
0"
b1100 C
0#
#1415000
07
1"
#1420000
1-
1&
0"
1#
b1100 !
b1100 %
#1425000
0&
17
02
10
0,
0-
0B
18
1"
#1430000
0"
0#
#1435000
07
1"
#1440000
00
12
1,
1&
0"
1#
#1445000
0,
0&
17
1>
0<
08
b1111111111111111111111111111111111111111111111111111110001111100 9
b10 5
1"
#1450000
0"
b111 C
0#
#1455000
07
1"
#1460000
11
02
1+
1&
0"
1#
b111 !
b111 %
#1465000
0+
0&
17
1'
1=
0>
b1010111100 :
1"
#1470000
0"
b1101 C
0#
#1475000
07
1"
#1480000
1.
1&
0"
1#
b1101 !
b1101 %
#1485000
0.
0&
17
1B
1"
