src/control_unit.v
// Define operation codes
`define ZERO 4'h0
`define ONE 4'h1
`define TWO 4'h2
`define THREE 4'h3
`define MEM_STORE 4'h1
`define MEM_LOAD 4'h2
`define MEM_CLEAR 4'h3
`define FOUR 4'h4
`define FIVE 4'h5
`define SIX 4'h6
`define SEVEN 4'h7
`define EIGHT 4'h8
`define NINE 4'h9
`define ADD 4'hA
`define DIV 4'hA
`define SUB 4'hB
`define DEC 4'hB
`define MUL 4'hC
`define NEG 4'hC
`define TOGGLE 4'hD
`define EQUAL 4'hE
`define CLEAR 4'hF

module control_unit (
    output                   display,          // OLED Display output
    output reg signed [31:0] operandF = 0,     // First operand
    output reg signed [31:0] operandS = 0,     // Second operand
    output reg               toggle = 0,
    output reg               negative = 0,
    input             [ 3:0] button,           // User input button (0-9, +, -, *, /, =)
    input                    is_pressed_next,  // Button press signal
    input                    clock,            // Clock signal
    input                    reset             // Reset signal
);

  reg [1:0] alu_op = 0;  // ALU operation state (0: +, 1: -, 2: *, 3: /)

  // State outputs
  reg s_initial, s_operandF, s_operation, s_operandS, s_result;
  reg is_pressed = 0;  // Initialize because it broke under Ryan
  reg [1:0] decimal = 0;
  reg signed [31:0] stored_value = 0;
  reg stored_negative = 0;

  localparam fixed_point_length = 2;
  // Vivado does not support exponentiation :((((
  // Workaround:
  localparam fixed_point_multiplier = 100; // 10^fixed_point_length

  reg [31:0] current_multiplier = fixed_point_multiplier / 10; //10^(fixed_point_length - decimal)

  // Next state inputs
  wire next_initial, next_operandF, next_operation, next_operandS, next_result;


  wire button_pressed = (is_pressed == 0 && is_pressed_next == 1);
  wire is_symbol = button_pressed && ((button == `DEC && toggle) || (button == `NEG && toggle));
  wire is_number = button_pressed && ((button >= `ZERO && button <= `NINE) && ~toggle);
  wire is_equal = button_pressed && (button == `EQUAL);
  wire is_op = button_pressed && (button == `ADD || (button == `SUB && ~toggle)  ||  ( button == `MUL && ~toggle));
  wire is_clear = button_pressed && (button == `CLEAR);
  wire is_toggled = button_pressed && (button == `TOGGLE);
  wire is_mem_op = button_pressed && toggle && (button == `MEM_STORE || button == `MEM_LOAD || button == `MEM_CLEAR);

  // always @(posedge clock or posedge reset) begin
  //   if (reset) begin
  //     s_initial = 1;
  //     s_operandF = 0;
  //     s_operation = 0;
  //     s_operandS = 0;
  //     s_result = 0;
  //     is_pressed = 0;
  //     toggle = 0;
  //     negative = 0;
  //     decimal = 0;
  //     stored_value = 0;
  //     current_multiplier = fixed_point_multiplier / 10;
  //   end else begin
  //     s_initial = next_initial;
  //     s_operandF = next_operandF;
  //     s_operation = next_operation;
  //     s_operandS = next_operandS;
  //     s_result = next_result;
  //     is_pressed = is_pressed_next;
  //   end
  // end

  //conditions for next state of FSM
  assign next_initial = reset || is_clear || (is_equal && s_initial) || 
                                             (is_op && s_initial) || 
                                             (~button_pressed && s_initial) || 
                                             (s_initial && is_toggled);
  assign next_operandF = ((is_number && s_initial) || 
                          (is_number && s_operandF) || 
                          (is_equal && s_operandF) || 
                          (~button_pressed && s_operandF) || 
                          (s_operandF && is_toggled) || 
                          (s_initial && is_symbol) ||
                          (s_operandF && is_symbol) || 
                          (s_initial && is_mem_op) || 
                          (s_operandF && is_mem_op)) && ~reset;
  assign next_operation = ((is_op && s_operandF) || 
                           (is_op && s_operation) || 
                           (is_equal && s_operation) || 
                           (is_op && s_result) || 
                           (~button_pressed && s_operation) || 
                           (s_operation && is_toggled)) && ~reset;
  assign next_operandS =  ((is_number && s_operation) || 
                           (is_number && s_operandS) || 
                           (is_op && s_operandS) || 
                           (~button_pressed && s_operandS) || 
                           (s_operandS && is_toggled) || 
                           (s_operation && is_symbol) ||
                           (s_operandS && is_symbol) || 
                           (s_operation && is_mem_op) ||
                           (s_operandS && is_mem_op)) && ~reset;
  assign next_result = ((is_equal && s_operandS) || 
                        (is_equal && s_result) || 
                        (is_number && s_result) || 
                        (~button_pressed & s_result) || 
                        (s_result && is_toggled) || 
                        (s_result && is_symbol) ||
                        (s_result && is_mem_op)) && ~reset;


  always @(posedge clock) begin
    //resets to initial state, along with changing any temporary inputs to 0
    if (reset) begin
      s_initial = 1;
      s_operandF = 0;
      s_operation = 0;
      s_operandS = 0;
      s_result = 0;
      is_pressed = 0;
      toggle = 0;
      negative = 0;
      decimal = 0;
      stored_value = 0;
      current_multiplier = fixed_point_multiplier / 10;
    end else begin
      if (s_initial && is_number) begin
        operandF = button * fixed_point_multiplier;
      end else if (is_toggled) begin
        toggle = ~toggle;
      end else if (s_operandF && is_number) begin
        if (decimal) begin
          operandF = operandF + button * current_multiplier;
          decimal  = decimal + 1;
          current_multiplier = current_multiplier / 10;
        end else begin
          operandF = operandF * 10 + button * fixed_point_multiplier;
        end
      end else if ((s_initial || s_operandF) && toggle && is_symbol && (button == `NEG)) begin
        negative = ~negative;
        toggle   = 0;
      end else if ((s_initial || s_operandF) && toggle && is_symbol && (button == `DEC)) begin
        if (decimal == 0) begin
          decimal = 1;
          current_multiplier = fixed_point_multiplier / 10;
        end
        toggle = 0;
      end else if ((s_initial || s_operandF) && toggle && is_mem_op && button == `MEM_LOAD) begin
        operandF = stored_value;
        negative = stored_negative;
        decimal  = fixed_point_length + 1;
        current_multiplier = 0;
        toggle   = 0;
      end else if ((s_operandF || s_result) && is_op) begin
        if (button == `ADD && toggle == 0) begin
          alu_op = 0;
          if (negative) begin
            operandF = -operandF;
            negative = 0;
          end
          decimal = 0;
          current_multiplier = fixed_point_multiplier / 10;
        end else if (button == `SUB && toggle == 0) begin
          alu_op = 1;
          if (negative) begin
            operandF = -operandF;
            negative = 0;
          end
          decimal = 0;
          current_multiplier = fixed_point_multiplier / 10;
        end else if (button == `MUL && toggle == 0) begin
          alu_op = 2;
          if (negative) begin
            operandF = -operandF;
            negative = 0;
          end
          decimal = 0;
          current_multiplier = fixed_point_multiplier / 10;
        end else if (button == `DIV && toggle == 1) begin
          alu_op = 3;
          if (negative) begin
            operandF = -operandF;
            negative = 0;
          end
          decimal = 0;
          current_multiplier = fixed_point_multiplier / 10;
        end
        toggle = 0;
      end else if (s_operation && is_number) begin
        operandS = button * fixed_point_multiplier;
      end else if (s_operandS && is_number) begin
        if (decimal) begin
          operandS = operandS + button * current_multiplier;
          decimal  = decimal + 1;
          current_multiplier = current_multiplier / 10;
        end else begin
          operandS = operandS * 10 + button * fixed_point_multiplier;
        end
      end else if ((s_operation || s_operandS) && toggle && is_symbol && (button == `NEG)) begin
        negative = ~negative;
        toggle   = 0;
      end else if ((s_operation || s_operandS) && toggle && is_symbol && (button == `DEC)) begin
        if (decimal == 0) begin
          decimal = 1;
          current_multiplier = fixed_point_multiplier / 10;
        end
        toggle = 0;
      end else if ((s_operation || s_operandS) && toggle && is_mem_op && button == `MEM_LOAD) begin
        operandS = stored_value;
        negative = stored_negative;
        decimal  = fixed_point_length + 1;
        current_multiplier = 0;
        toggle   = 0;
      end else if (s_operandS && is_equal) begin
        if (negative) begin
          operandS = -operandS;
          negative = 0;
          decimal  = 0;
          current_multiplier = fixed_point_multiplier / 10;
        end
        case (alu_op)
          0: operandF = operandF + operandS;
          1: operandF = operandF - operandS;
          2: operandF = (operandF * operandS) / (fixed_point_multiplier);
          3: operandF = (operandF * (fixed_point_multiplier) / operandS);
        endcase
        operandS = 0;
        alu_op   = 0;
        toggle   = 0;
        negative = 0;
        decimal  = 0;
        current_multiplier = fixed_point_multiplier / 10;
      end else if (s_result && toggle && is_mem_op && button == `MEM_STORE) begin
        stored_value = operandF;
        if (operandF < 0) begin
          stored_value = -stored_value;
        end
        stored_negative = (operandF < 0);
        toggle = 0;
      end else if (is_clear) begin
        operandF = 0;
        operandS = 0;
        alu_op   = 0;
        toggle   = 0;
        negative = 0;
        decimal  = 0;
        current_multiplier = fixed_point_multiplier / 10;
      end else if (toggle && is_mem_op && button == `MEM_CLEAR) begin
        stored_value = 0;
        stored_negative = 0;
        toggle = 0;
      end
      s_initial = next_initial;
      s_operandF = next_operandF;
      s_operation = next_operation;
      s_operandS = next_operandS;
      s_result = next_result;
      is_pressed = is_pressed_next;
    end
  end

  assign display = s_operandS;

endmodule

src/control_unit_tb.v
`timescale 1ns / 1ps

module control_unit_test;

  // Testbench Signals
  reg [3:0] button = 4'h0;
  reg is_pressed_next = 0;
  reg clock = 0;
  reg reset = 1;// we need to remove this so that the control unit always initilizes to the "initial state" when powered

  // Instantiate Device Under Test (DUT)
  control_unit dut (
      .button(button),
      .is_pressed_next(is_pressed_next),
      .clock(clock),
      .reset(reset)
  );

  // Clock generation (100 MHz)
  always #5 clock = ~clock;

  // Function to simulate button press
  task press_button;
    input [3:0] btn;
    begin
      #10 button = btn;
      is_pressed_next = 1;
      #10 is_pressed_next = 0;  // Mimic button press duration
    end
  endtask


  // Initial block for simulation control
  initial begin
    // Setup waveform dump
    $dumpfile("bin/control_unit.vcd");
    $dumpvars;

    // Reset the DUT
    #10 reset = 0;

    // pos + pos
    // 9 + 7 = 16
    press_button(`NINE);
    press_button(`ADD_DIV);
    press_button(`SEVEN);
    press_button(`EQUAL);
    press_button(`CLEAR);

    // pos + neg 
    // 9 + -7 = 2
    press_button(`NINE);
    press_button(`ADD_DIV);
    press_button(`SEVEN);
    press_button(`TOGGLE);
    press_button(`MUL_NEG);
    press_button(`EQUAL);
    press_button(`CLEAR);

    // neg + neg
    // -9 + -7 = -16
    press_button(`NINE);
    press_button(`TOGGLE);
    press_button(`MUL_NEG);
    press_button(`ADD_DIV);
    press_button(`SEVEN);
    press_button(`TOGGLE);
    press_button(`MUL_NEG);
    press_button(`EQUAL);
    press_button(`CLEAR);

    // neg + pos
    // -9 + 7 = -2
    press_button(`NINE);
    press_button(`TOGGLE);
    press_button(`MUL_NEG);
    press_button(`ADD_DIV);
    press_button(`SEVEN);
    press_button(`EQUAL);
    press_button(`CLEAR);

    // pos - pos
    // 9 - 7 = 2
    press_button(`NINE);
    press_button(`SUB_DEC);
    press_button(`SEVEN);
    press_button(`EQUAL);
    press_button(`CLEAR);

    // pos - neg
    // 9 - -7 = 16
    press_button(`NINE);
    press_button(`SUB_DEC);
    press_button(`SEVEN);
    press_button(`TOGGLE);
    press_button(`MUL_NEG);
    press_button(`EQUAL);
    press_button(`CLEAR);


    // neg - neg
    // -9 - -7 = -2
    press_button(`NINE);
    press_button(`TOGGLE);
    press_button(`MUL_NEG);
    press_button(`SUB_DEC);
    press_button(`SEVEN);
    press_button(`TOGGLE);
    press_button(`MUL_NEG);
    press_button(`EQUAL);
    press_button(`CLEAR);

    // neg - pos
    // -9 - 7 = -16
    press_button(`NINE);
    press_button(`TOGGLE);
    press_button(`MUL_NEG);
    press_button(`SUB_DEC);
    press_button(`SEVEN);
    press_button(`EQUAL);
    press_button(`CLEAR);


    // pos * pos
    // 9 * 7 = 63
    press_button(`NINE);
    press_button(`MUL_NEG);
    press_button(`SEVEN);
    press_button(`EQUAL);
    press_button(`CLEAR);


    // pos * neg
    // 9 * -7 = -63
    press_button(`NINE);
    press_button(`MUL_NEG);
    press_button(`SEVEN);
    press_button(`TOGGLE);
    press_button(`MUL_NEG);
    press_button(`EQUAL);
    press_button(`CLEAR);

    // neg * neg
    // -9 * -7 = 63
    press_button(`NINE);
    press_button(`TOGGLE);
    press_button(`MUL_NEG);
    press_button(`MUL_NEG);
    press_button(`SEVEN);
    press_button(`TOGGLE);
    press_button(`MUL_NEG);
    press_button(`EQUAL);
    press_button(`CLEAR);

    // neg * pos
    // -9 * 7 = -63
    press_button(`NINE);
    press_button(`TOGGLE);
    press_button(`MUL_NEG);
    press_button(`MUL_NEG);
    press_button(`SEVEN);
    press_button(`EQUAL);
    press_button(`CLEAR);

    // pos / pos
    // 9 / 7 = 1
    press_button(`NINE);
    press_button(`TOGGLE);
    press_button(`ADD_DIV);
    press_button(`SEVEN);
    press_button(`EQUAL);
    press_button(`CLEAR);

    // pos / neg
    // 9 / -7 = -1
    press_button(`NINE);
    press_button(`TOGGLE);
    press_button(`ADD_DIV);
    press_button(`SEVEN);
    press_button(`TOGGLE);
    press_button(`MUL_NEG);
    press_button(`EQUAL);
    press_button(`CLEAR);

    // neg / neg
    // -9 / -7 = 1
    press_button(`NINE);
    press_button(`TOGGLE);
    press_button(`MUL_NEG);
    press_button(`TOGGLE);
    press_button(`ADD_DIV);
    press_button(`SEVEN);
    press_button(`TOGGLE);
    press_button(`MUL_NEG);
    press_button(`EQUAL);
    press_button(`CLEAR);

    // neg / pos
    // -9 / 7 = -1
    press_button(`NINE);
    press_button(`TOGGLE);
    press_button(`MUL_NEG);
    press_button(`TOGGLE);
    press_button(`ADD_DIV);
    press_button(`SEVEN);
    press_button(`EQUAL);
    press_button(`CLEAR);


    // 2.5 + 3.5
    press_button(`TWO);
    press_button(`TOGGLE);
    press_button(`SUB_DEC);
    press_button(`FIVE);
    press_button(`ADD_DIV);
    press_button(`THREE);
    press_button(`TOGGLE);
    press_button(`SUB_DEC);
    press_button(`FIVE);
    press_button(`EQUAL);
    press_button(`CLEAR);

    // .9 + .7
    press_button(`TOGGLE);
    press_button(`SUB_DEC);
    press_button(`NINE);
    press_button(`ADD_DIV);
    press_button(`TOGGLE);
    press_button(`SUB_DEC);
    press_button(`SEVEN);
    press_button(`EQUAL);
    press_button(`CLEAR);

    // .09 + .07
    press_button(`TOGGLE);
    press_button(`SUB_DEC);
    press_button(`ZERO);
    press_button(`NINE);
    press_button(`ADD_DIV);
    press_button(`TOGGLE);
    press_button(`SUB_DEC);
    press_button(`ZERO);
    press_button(`SEVEN);
    press_button(`EQUAL);
    press_button(`CLEAR);

    // .09 + 4.93 - 5.01
    press_button(`TOGGLE);
    press_button(`SUB_DEC);
    press_button(`ZERO);
    press_button(`NINE);
    press_button(`ADD_DIV);
    press_button(`FOUR);
    press_button(`TOGGLE);
    press_button(`SUB_DEC);
    press_button(`NINE);
    press_button(`THREE);
    press_button(`EQUAL);
    press_button(`SUB_DEC);
    press_button(`FIVE);
    press_button(`TOGGLE);
    press_button(`SUB_DEC);
    press_button(`ZERO);
    press_button(`ONE);
    press_button(`EQUAL);
    press_button(`CLEAR);

    // 5.09 * 1.25
    press_button(`FIVE);
    press_button(`TOGGLE);
    press_button(`SUB_DEC);
    press_button(`ZERO);
    press_button(`NINE);
    press_button(`MUL_NEG);
    press_button(`ONE);
    press_button(`TOGGLE);
    press_button(`SUB_DEC);
    press_button(`TWO);
    press_button(`FIVE);
    press_button(`EQUAL);
    press_button(`CLEAR);

    // -5.09 / 1.25
    press_button(`TOGGLE);
    press_button(`MUL_NEG);
    press_button(`FIVE);
    press_button(`TOGGLE);
    press_button(`SUB_DEC);
    press_button(`ZERO);
    press_button(`NINE);
    press_button(`TOGGLE);
    press_button(`ADD_DIV);
    press_button(`ONE);
    press_button(`TOGGLE);
    press_button(`SUB_DEC);
    press_button(`TWO);
    press_button(`FIVE);
    press_button(`EQUAL);
    press_button(`CLEAR);

    //-.09 / 1.25
    press_button(`TOGGLE);
    press_button(`MUL_NEG);
    press_button(`TOGGLE);
    press_button(`SUB_DEC);
    press_button(`ZERO);
    press_button(`NINE);
    press_button(`TOGGLE);
    press_button(`ADD_DIV);
    press_button(`ONE);
    press_button(`TOGGLE);
    press_button(`SUB_DEC);
    press_button(`TWO);
    press_button(`FIVE);
    press_button(`EQUAL);
    press_button(`CLEAR);

    // 5+3 = 8 -> MEM
    // CLEAR
    // 2 + 5 = 7
    // MEM -> 8 + 4 = 12
    // MEM_CLEAR = 0
    // MEM -> 0 + 4 = 4
    press_button(`FIVE);
    press_button(`ADD_DIV);
    press_button(`THREE);
    press_button(`EQUAL);
    press_button(`TOGGLE);
    press_button(`MEM_STORE);
    press_button(`CLEAR);
    press_button(`TWO);
    press_button(`ADD_DIV);
    press_button(`FIVE);
    press_button(`EQUAL);
    press_button(`CLEAR);
    press_button(`TOGGLE);
    press_button(`MEM_LOAD);
    press_button(`ADD_DIV);
    press_button(`FOUR);
    press_button(`EQUAL);
    press_button(`CLEAR);
    press_button(`TOGGLE);
    press_button(`MEM_CLEAR);
    press_button(`TOGGLE);
    press_button(`MEM_LOAD);
    press_button(`ADD_DIV);
    press_button(`FOUR);
    press_button(`EQUAL);
    press_button(`CLEAR);

    #10 reset = 1;
    // End simulation after a specified time
    #50 $finish;
  end

endmodule

calculator/calculator.sim/sim_1/behav/xsim/dump.vcd
$date
   Tue Dec  5 20:50:40 2023
$end
$version
  2020.2
$end
$timescale
  1ps
$end
$scope module control_unit_test $end
$var reg 4 ! button [3:0] $end
$var reg 1 " is_pressed_next $end
$var reg 1 # clock $end
$var reg 1 $ reset $end
$scope module dut $end
$var wire 1 % display $end
$var reg 32 & operandF [31:0] $end
$var reg 32 ' operandS [31:0] $end
$var reg 1 ( toggle $end
$var reg 1 ) negative $end
$var wire 4 * button [3:0] $end
$var wire 1 + is_pressed_next $end
$var wire 1 , clock $end
$var wire 1 - reset $end
$var reg 2 . alu_op [1:0] $end
$var reg 1 / s_initial $end
$var reg 1 0 s_operandF $end
$var reg 1 1 s_operation $end
$var reg 1 2 s_operandS $end
$var reg 1 3 s_result $end
$var reg 1 4 is_pressed $end
$var reg 2 5 decimal [1:0] $end
$var reg 32 6 stored_value [31:0] $end
$var reg 1 7 stored_negative $end
$var reg 32 8 current_multiplier [31:0] $end
$var wire 1 9 next_initial $end
$var wire 1 : next_operandF $end
$var wire 1 ; next_operation $end
$var wire 1 < next_operandS $end
$var wire 1 = next_result $end
$var wire 1 > button_pressed $end
$var wire 1 ? is_symbol $end
$var wire 1 @ is_number $end
$var wire 1 A is_equal $end
$var wire 1 B is_op $end
$var wire 1 C is_clear $end
$var wire 1 D is_toggled $end
$var wire 1 E is_mem_op $end
$var parameter 32 F fixed_point_length [31:0] $end
$var parameter 32 G fixed_point_multiplier [31:0] $end
$upscope $end
$scope task press_button $end
$var reg 4 H btn [3:0] $end
$upscope $end
$upscope $end
$enddefinitions $end
#0
$dumpvars
b0 !
0"
0#
1$
x%
b0 &
b0 '
0(
0)
b0 *
0+
0,
1-
b0 .
x/
x0
x1
x2
x3
04
b0 5
b0 6
07
b1010 8
19
0:
0;
0<
0=
0>
0?
0@
0A
0B
0C
0D
0E
b10 F
b1100100 G
bx H
$end
#5000
1#
0%
0(
0)
1,
1/
00
01
02
03
04
b0 5
b0 6
b1010 8
19
0:
0;
0<
0=
#10000
0#
0$
0,
0-
19
0:
0;
0<
0=
b1001 H
#15000
1#
1,
1/
00
01
02
03
04
#20000
b1001 !
1"
0#
b1001 *
1+
0,
09
1:
0;
0<
0=
1>
0?
1@
0A
0B
0C
0D
0E
#25000
1#
b1110000100 &
1,
0/
10
01
02
03
14
09
1:
0;
0<
0=
0>
0?
0@
0A
0B
0C
0D
0E
#30000
0"
0#
0+
0,
0>
b1010 H
#35000
1#
1,
0/
10
01
02
03
04
0>
#40000
b1010 !
1"
0#
b1010 *
1+
0,
09
0:
1;
0<
0=
1>
0?
0@
0A
1B
0C
0D
0E
#45000
1#
0(
1,
b0 .
0/
00
11
02
03
14
b0 5
b1010 8
09
0:
1;
0<
0=
0>
0?
0@
0A
0B
0C
0D
0E
#50000
0"
0#
0+
0,
0>
b111 H
#55000
1#
1,
0/
00
11
02
03
04
0>
#60000
b111 !
1"
0#
b111 *
1+
0,
09
0:
0;
1<
0=
1>
0?
1@
0A
0B
0C
0D
0E
#65000
1#
1%
b1010111100 '
1,
0/
00
01
12
03
14
09
0:
0;
1<
0=
0>
0?
0@
0A
0B
0C
0D
0E
#70000
0"
0#
0+
0,
0>
b1110 H
#75000
1#
1,
0/
00
01
12
03
04
0>
#80000
b1110 !
1"
0#
b1110 *
1+
0,
09
0:
0;
0<
1=
1>
0?
0@
1A
0B
0C
0D
0E
#85000
1#
0%
b11001000000 &
b0 '
0(
0)
1,
b0 .
0/
00
01
02
13
14
b0 5
b1010 8
09
0:
0;
0<
1=
0>
0?
0@
0A
0B
0C
0D
0E
#90000
0"
0#
0+
0,
0>
b1111 H
#95000
1#
1,
0/
00
01
02
13
04
0>
#100000
b1111 !
1"
0#
b1111 *
1+
0,
19
0:
0;
0<
0=
1>
0?
0@
0A
0B
1C
0D
0E
#105000
1#
b0 &
b0 '
0(
0)
1,
b0 .
1/
00
01
02
03
14
b0 5
b1010 8
19
0:
0;
0<
0=
0>
0?
0@
0A
0B
0C
0D
0E
#110000
0"
0#
0+
0,
0>
b1001 H
#115000
1#
1,
1/
00
01
02
03
04
0>
#120000
b1001 !
1"
0#
b1001 *
1+
0,
09
1:
0;
0<
0=
1>
0?
1@
0A
0B
0C
0D
0E
#125000
1#
b1110000100 &
1,
0/
10
01
02
03
14
09
1:
0;
0<
0=
0>
0?
0@
0A
0B
0C
0D
0E
#130000
0"
0#
0+
0,
0>
b1010 H
#135000
1#
1,
0/
10
01
02
03
04
0>
#140000
b1010 !
1"
0#
b1010 *
1+
0,
09
0:
1;
0<
0=
1>
0?
0@
0A
1B
0C
0D
0E
#145000
1#
0(
1,
b0 .
0/
00
11
02
03
14
b0 5
b1010 8
09
0:
1;
0<
0=
0>
0?
0@
0A
0B
0C
0D
0E
#150000
0"
0#
0+
0,
0>
b111 H
#155000
1#
1,
0/
00
11
02
03
04
0>
#160000
b111 !
1"
0#
b111 *
1+
0,
09
0:
0;
1<
0=
1>
0?
1@
0A
0B
0C
0D
0E
#165000
1#
1%
b1010111100 '
1,
0/
00
01
12
03
14
09
0:
0;
1<
0=
0>
0?
0@
0A
0B
0C
0D
0E
#170000
0"
0#
0+
0,
0>
b1101 H
#175000
1#
1,
0/
00
01
12
03
04
0>
#180000
b1101 !
1"
0#
b1101 *
1+
0,
09
0:
0;
1<
0=
1>
0?
0@
0A
0B
0C
1D
0E
#185000
1#
1(
1,
0/
00
01
12
03
14
09
0:
0;
1<
0=
0>
0?
0@
0A
0B
0C
0D
0E
#190000
0"
0#
0+
0,
0>
b1100 H
#195000
1#
1,
0/
00
01
12
03
04
0>
#200000
b1100 !
1"
0#
b1100 *
1+
0,
09
0:
0;
1<
0=
1>
1?
0@
0A
0B
0C
0D
0E
#205000
1#
0(
1)
1,
0/
00
01
12
03
14
09
0:
0;
1<
0=
0>
0?
0@
0A
0B
0C
0D
0E
#210000
0"
0#
0+
0,
0>
b1110 H
#215000
1#
1,
0/
00
01
12
03
04
0>
#220000
b1110 !
1"
0#
b1110 *
1+
0,
09
0:
0;
0<
1=
1>
0?
0@
1A
0B
0C
0D
0E
#225000
1#
0%
b11001000000 &
b0 '
0(
0)
1,
b0 .
0/
00
01
02
13
14
b0 5
b1010 8
09
0:
0;
0<
1=
0>
0?
0@
0A
0B
0C
0D
0E
#230000
0"
0#
0+
0,
0>
b1111 H
#235000
1#
1,
0/
00
01
02
13
04
0>
#240000
b1111 !
1"
0#
b1111 *
1+
0,
19
0:
0;
0<
0=
1>
0?
0@
0A
0B
1C
0D
0E
#245000
1#
b0 &
b0 '
0(
0)
1,
b0 .
1/
00
01
02
03
14
b0 5
b1010 8
19
0:
0;
0<
0=
0>
0?
0@
0A
0B
0C
0D
0E
#250000
0"
0#
0+
0,
0>
b1001 H
#255000
1#
1,
1/
00
01
02
03
04
0>
#260000
b1001 !
1"
0#
b1001 *
1+
0,
09
1:
0;
0<
0=
1>
0?
1@
0A
0B
0C
0D
0E
#265000
1#
b1110000100 &
1,
0/
10
01
02
03
14
09
1:
0;
0<
0=
0>
0?
0@
0A
0B
0C
0D
0E
#270000
0"
0#
0+
0,
0>
b1101 H
#275000
1#
1,
0/
10
01
02
03
04
0>
#280000
b1101 !
1"
0#
b1101 *
1+
0,
09
1:
0;
0<
0=
1>
0?
0@
0A
0B
0C
1D
0E
#285000
1#
1(
1,
0/
10
01
02
03
14
09
1:
0;
0<
0=
0>
0?
0@
0A
0B
0C
0D
0E
#290000
0"
0#
0+
0,
0>
b1100 H
#295000
1#
1,
0/
10
01
02
03
04
0>
#300000
b1100 !
1"
0#
b1100 *
1+
0,
09
1:
0;
0<
0=
1>
1?
0@
0A
0B
0C
0D
0E
#305000
1#
0(
1)
1,
0/
10
01
02
03
14
09
1:
0;
0<
0=
0>
0?
0@
0A
0B
0C
0D
0E
#310000
0"
0#
0+
0,
0>
b1010 H
#315000
1#
1,
0/
10
01
02
03
04
0>
#320000
b1010 !
1"
0#
b1010 *
1+
0,
09
0:
1;
0<
0=
1>
0?
0@
0A
1B
0C
0D
0E
#325000
1#
b11111111111111111111110001111100 &
0(
0)
1,
b0 .
0/
00
11
02
03
14
b0 5
b1010 8
09
0:
1;
0<
0=
0>
0?
0@
0A
0B
0C
0D
0E
#330000
0"
0#
0+
0,
0>
b111 H
#335000
1#
1,
0/
00
11
02
03
04
0>
#340000
b111 !
1"
0#
b111 *
1+
0,
09
0:
0;
1<
0=
1>
0?
1@
0A
0B
0C
0D
0E
#345000
1#
1%
b1010111100 '
1,
0/
00
01
12
03
14
09
0:
0;
1<
0=
0>
0?
0@
0A
0B
0C
0D
0E
#350000
0"
0#
0+
0,
0>
b1101 H
#355000
1#
1,
0/
00
01
12
03
04
0>
#360000
b1101 !
1"
0#
b1101 *
1+
0,
09
0:
0;
1<
0=
1>
0?
0@
0A
0B
0C
1D
0E
#365000
1#
1(
1,
0/
00
01
12
03
14
09
0:
0;
1<
0=
0>
0?
0@
0A
0B
0C
0D
0E
#370000
0"
0#
0+
0,
0>
b1100 H
#375000
1#
1,
0/
00
01
12
03
04
0>
#380000
b1100 !
1"
0#
b1100 *
1+
0,
09
0:
0;
1<
0=
1>
1?
0@
0A
0B
0C
0D
0E
#385000
1#
0(
1)
1,
0/
00
01
12
03
14
09
0:
0;
1<
0=
0>
0?
0@
0A
0B
0C
0D
0E
#390000
0"
0#
0+
0,
0>
b1110 H
#395000
1#
1,
0/
00
01
12
03
04
0>
#400000
b1110 !
1"
0#
b1110 *
1+
0,
09
0:
0;
0<
1=
1>
0?
0@
1A
0B
0C
0D
0E
#405000
1#
0%
b11111111111111111111111100111000 &
b0 '
0(
0)
1,
b0 .
0/
00
01
02
13
14
b0 5
b1010 8
09
0:
0;
0<
1=
0>
0?
0@
0A
0B
0C
0D
0E
#410000
0"
0#
0+
0,
0>
b1111 H
#415000
1#
1,
0/
00
01
02
13
04
0>
#420000
b1111 !
1"
0#
b1111 *
1+
0,
19
0:
0;
0<
0=
1>
0?
0@
0A
0B
1C
0D
0E
#425000
1#
b0 &
b0 '
0(
0)
1,
b0 .
1/
00
01
02
03
14
b0 5
b1010 8
19
0:
0;
0<
0=
0>
0?
0@
0A
0B
0C
0D
0E
#430000
0"
0#
0+
0,
0>
b1001 H
#435000
1#
1,
1/
00
01
02
03
04
0>
#440000
b1001 !
1"
0#
b1001 *
1+
0,
09
1:
0;
0<
0=
1>
0?
1@
0A
0B
0C
0D
0E
#445000
1#
b1110000100 &
1,
0/
10
01
02
03
14
09
1:
0;
0<
0=
0>
0?
0@
0A
0B
0C
0D
0E
#450000
0"
0#
0+
0,
0>
b1101 H
#455000
1#
1,
0/
10
01
02
03
04
0>
#460000
b1101 !
1"
0#
b1101 *
1+
0,
09
1:
0;
0<
0=
1>
0?
0@
0A
0B
0C
1D
0E
#465000
1#
1(
1,
0/
10
01
02
03
14
09
1:
0;
0<
0=
0>
0?
0@
0A
0B
0C
0D
0E
#470000
0"
0#
0+
0,
0>
b1100 H
#475000
1#
1,
0/
10
01
02
03
04
0>
#480000
b1100 !
1"
0#
b1100 *
1+
0,
09
1:
0;
0<
0=
1>
1?
0@
0A
0B
0C
0D
0E
#485000
1#
0(
1)
1,
0/
10
01
02
03
14
09
1:
0;
0<
0=
0>
0?
0@
0A
0B
0C
0D
0E
#490000
0"
0#
0+
0,
0>
b1010 H
#495000
1#
1,
0/
10
01
02
03
04
0>
#500000
b1010 !
1"
0#
b1010 *
1+
0,
09
0:
1;
0<
0=
1>
0?
0@
0A
1B
0C
0D
0E
#505000
1#
b11111111111111111111110001111100 &
0(
0)
1,
b0 .
0/
00
11
02
03
14
b0 5
b1010 8
09
0:
1;
0<
0=
0>
0?
0@
0A
0B
0C
0D
0E
#510000
0"
0#
0+
0,
0>
b111 H
#515000
1#
1,
0/
00
11
02
03
04
0>
#520000
b111 !
1"
0#
b111 *
1+
0,
09
0:
0;
1<
0=
1>
0?
1@
0A
0B
0C
0D
0E
#525000
1#
1%
b1010111100 '
1,
0/
00
01
12
03
14
09
0:
0;
1<
0=
0>
0?
0@
0A
0B
0C
0D
0E
#530000
0"
0#
0+
0,
0>
b1110 H
#535000
1#
1,
0/
00
01
12
03
04
0>
#540000
b1110 !
1"
0#
b1110 *
1+
0,
09
0:
0;
0<
1=
1>
0?
0@
1A
0B
0C
0D
0E
#545000
1#
0%
b11111111111111111111111100111000 &
b0 '
0(
0)
1,
b0 .
0/
00
01
02
13
14
b0 5
b1010 8
09
0:
0;
0<
1=
0>
0?
0@
0A
0B
0C
0D
0E
#550000
0"
0#
0+
0,
0>
b1111 H
#555000
1#
1,
0/
00
01
02
13
04
0>
#560000
b1111 !
1"
0#
b1111 *
1+
0,
19
0:
0;
0<
0=
1>
0?
0@
0A
0B
1C
0D
0E
#565000
1#
b0 &
b0 '
0(
0)
1,
b0 .
1/
00
01
02
03
14
b0 5
b1010 8
19
0:
0;
0<
0=
0>
0?
0@
0A
0B
0C
0D
0E
#570000
0"
0#
0+
0,
0>
b1001 H
#575000
1#
1,
1/
00
01
02
03
04
0>
#580000
b1001 !
1"
0#
b1001 *
1+
0,
09
1:
0;
0<
0=
1>
0?
1@
0A
0B
0C
0D
0E
#585000
1#
b1110000100 &
1,
0/
10
01
02
03
14
09
1:
0;
0<
0=
0>
0?
0@
0A
0B
0C
0D
0E
#590000
0"
0#
0+
0,
0>
b1011 H
#595000
1#
1,
0/
10
01
02
03
04
0>
